<?xml version="1.0" encoding="utf-8" ?>
<dwsync>
<file name="adelante.png" server="web1420.ixwebhosting.com//imagenes360.net/tresdecito/" local="131353136485754983" remote="131353176600000000" Dst="0" />
<file name="adelante.svg" server="web1420.ixwebhosting.com//imagenes360.net/tresdecito/" local="131353136486175007" remote="131353176600000000" Dst="0" />
<file name="adelante0.png" server="web1420.ixwebhosting.com//imagenes360.net/tresdecito/" local="131353136486195008" remote="131353176600000000" Dst="0" />
<file name="adelante0.svg" server="web1420.ixwebhosting.com//imagenes360.net/tresdecito/" local="131353136486205009" remote="131353176600000000" Dst="0" />
<file name="adelante0__o.png" server="web1420.ixwebhosting.com//imagenes360.net/tresdecito/" local="131353136486225010" remote="131353176600000000" Dst="0" />
<file name="adelante0__o.svg" server="web1420.ixwebhosting.com//imagenes360.net/tresdecito/" local="131353136486235011" remote="131353176600000000" Dst="0" />
<file name="adelante1.png" server="web1420.ixwebhosting.com//imagenes360.net/tresdecito/" local="131353136486245011" remote="131353176600000000" Dst="0" />
<file name="adelante1.svg" server="web1420.ixwebhosting.com//imagenes360.net/tresdecito/" local="131353136486255012" remote="131353176600000000" Dst="0" />
<file name="adelante1__o.png" server="web1420.ixwebhosting.com//imagenes360.net/tresdecito/" local="131353136486265012" remote="131353176600000000" Dst="0" />
<file name="adelante1__o.svg" server="web1420.ixwebhosting.com//imagenes360.net/tresdecito/" local="131353136486275013" remote="131353176600000000" Dst="0" />
<file name="adelante2.png" server="web1420.ixwebhosting.com//imagenes360.net/tresdecito/" local="131353136486285014" remote="131353176600000000" Dst="0" />
<file name="adelante2.svg" server="web1420.ixwebhosting.com//imagenes360.net/tresdecito/" local="131353136486285014" remote="131353176600000000" Dst="0" />
<file name="adelante2__o.png" server="web1420.ixwebhosting.com//imagenes360.net/tresdecito/" local="131353136486295014" remote="131353176600000000" Dst="0" />
<file name="adelante2__o.svg" server="web1420.ixwebhosting.com//imagenes360.net/tresdecito/" local="131353136486305015" remote="131353176600000000" Dst="0" />
<file name="adelante3.png" server="web1420.ixwebhosting.com//imagenes360.net/tresdecito/" local="131353136486315015" remote="131353176600000000" Dst="0" />
<file name="adelante3.svg" server="web1420.ixwebhosting.com//imagenes360.net/tresdecito/" local="131353136486325016" remote="131353176600000000" Dst="0" />
<file name="adelante3__o.png" server="web1420.ixwebhosting.com//imagenes360.net/tresdecito/" local="131353136486335016" remote="131353176600000000" Dst="0" />
<file name="adelante3__o.svg" server="web1420.ixwebhosting.com//imagenes360.net/tresdecito/" local="131353136486345017" remote="131353176600000000" Dst="0" />
<file name="adelante4.png" server="web1420.ixwebhosting.com//imagenes360.net/tresdecito/" local="131353136486375019" remote="131353176600000000" Dst="0" />
<file name="adelante4.svg" server="web1420.ixwebhosting.com//imagenes360.net/tresdecito/" local="131353136486385019" remote="131353176600000000" Dst="0" />
<file name="adelante4__o.png" server="web1420.ixwebhosting.com//imagenes360.net/tresdecito/" local="131353136486395020" remote="131353176600000000" Dst="0" />
<file name="adelante4__o.svg" server="web1420.ixwebhosting.com//imagenes360.net/tresdecito/" local="131353136486405020" remote="131353176600000000" Dst="0" />
<file name="adelante__o.png" server="web1420.ixwebhosting.com//imagenes360.net/tresdecito/" local="131353136486415021" remote="131353176600000000" Dst="0" />
<file name="adelante__o.svg" server="web1420.ixwebhosting.com//imagenes360.net/tresdecito/" local="131353136486425022" remote="131353176600000000" Dst="0" />
<file name="alpha_background_000000_150.png" server="web1420.ixwebhosting.com//imagenes360.net/tresdecito/" local="131353136486435022" remote="131353176600000000" Dst="0" />
<file name="alpha_background_ffffff_180.png" server="web1420.ixwebhosting.com//imagenes360.net/tresdecito/" local="131353136486435022" remote="131353176600000000" Dst="0" />
<file name="Ambiente_01_PH_o_0.jpg" server="web1420.ixwebhosting.com//imagenes360.net/tresdecito/" local="131353136517476798" remote="131353176600000000" Dst="0" />
<file name="Ambiente_01_PH_o_1.jpg" server="web1420.ixwebhosting.com//imagenes360.net/tresdecito/" local="131353136518306845" remote="131353176600000000" Dst="0" />
<file name="Ambiente_01_PH_o_2.jpg" server="web1420.ixwebhosting.com//imagenes360.net/tresdecito/" local="131353136518896879" remote="131353176600000000" Dst="0" />
<file name="Ambiente_01_PH_o_3.jpg" server="web1420.ixwebhosting.com//imagenes360.net/tresdecito/" local="131353136519476912" remote="131353176600000000" Dst="0" />
<file name="Ambiente_01_PH_o_4.jpg" server="web1420.ixwebhosting.com//imagenes360.net/tresdecito/" local="131353136520066946" remote="131353176600000000" Dst="0" />
<file name="Ambiente_01_PH_o_5.jpg" server="web1420.ixwebhosting.com//imagenes360.net/tresdecito/" local="131353136520696982" remote="131353176600000000" Dst="0" />
<file name="Ambiente_PH3_o_0.jpg" server="web1420.ixwebhosting.com//imagenes360.net/tresdecito/" local="131353136580180384" remote="131353176600000000" Dst="0" />
<file name="Ambiente_PH3_o_1.jpg" server="web1420.ixwebhosting.com//imagenes360.net/tresdecito/" local="131353136580770418" remote="131353176600000000" Dst="0" />
<file name="Ambiente_PH3_o_3.jpg" server="web1420.ixwebhosting.com//imagenes360.net/tresdecito/" local="131353136582020489" remote="131353176600000000" Dst="0" />
<file name="Ambiente_PH3_o_2.jpg" server="web1420.ixwebhosting.com//imagenes360.net/tresdecito/" local="131353136581440456" remote="131353176600000000" Dst="0" />
<file name="atras.png" server="web1420.ixwebhosting.com//imagenes360.net/tresdecito/" local="131353136486445023" remote="131353176600000000" Dst="0" />
<file name="atras.svg" server="web1420.ixwebhosting.com//imagenes360.net/tresdecito/" local="131353136486455023" remote="131353176600000000" Dst="0" />
<file name="Ambiente_PH3_o_4.jpg" server="web1420.ixwebhosting.com//imagenes360.net/tresdecito/" local="131353136583110552" remote="131353176600000000" Dst="0" />
<file name="atras0.png" server="web1420.ixwebhosting.com//imagenes360.net/tresdecito/" local="131353136486465024" remote="131353176600000000" Dst="0" />
<file name="Ambiente_PH3_o_5.jpg" server="web1420.ixwebhosting.com//imagenes360.net/tresdecito/" local="131353136583760589" remote="131353176600000000" Dst="0" />
<file name="atras0.svg" server="web1420.ixwebhosting.com//imagenes360.net/tresdecito/" local="131353136486475024" remote="131353176600000000" Dst="0" />
<file name="atras0__o.png" server="web1420.ixwebhosting.com//imagenes360.net/tresdecito/" local="131353136486485025" remote="131353176600000000" Dst="0" />
<file name="atras0__o.svg" server="web1420.ixwebhosting.com//imagenes360.net/tresdecito/" local="131353136486495026" remote="131353176600000000" Dst="0" />
<file name="atras1.png" server="web1420.ixwebhosting.com//imagenes360.net/tresdecito/" local="131353136486505026" remote="131353176600000000" Dst="0" />
<file name="atras1.svg" server="web1420.ixwebhosting.com//imagenes360.net/tresdecito/" local="131353136486625033" remote="131353176600000000" Dst="0" />
<file name="atras1__o.png" server="web1420.ixwebhosting.com//imagenes360.net/tresdecito/" local="131353136486635034" remote="131353176600000000" Dst="0" />
<file name="atras1__o.svg" server="web1420.ixwebhosting.com//imagenes360.net/tresdecito/" local="131353136486645034" remote="131353176600000000" Dst="0" />
<file name="atras2.png" server="web1420.ixwebhosting.com//imagenes360.net/tresdecito/" local="131353136486655035" remote="131353176600000000" Dst="0" />
<file name="atras2.svg" server="web1420.ixwebhosting.com//imagenes360.net/tresdecito/" local="131353136486665035" remote="131353176600000000" Dst="0" />
<file name="atras2__o.png" server="web1420.ixwebhosting.com//imagenes360.net/tresdecito/" local="131353136486675036" remote="131353176600000000" Dst="0" />
<file name="atras2__o.svg" server="web1420.ixwebhosting.com//imagenes360.net/tresdecito/" local="131353136486685036" remote="131353176600000000" Dst="0" />
<file name="atras3.png" server="web1420.ixwebhosting.com//imagenes360.net/tresdecito/" local="131353136486695037" remote="131353176600000000" Dst="0" />
<file name="atras3.svg" server="web1420.ixwebhosting.com//imagenes360.net/tresdecito/" local="131353136486705038" remote="131353176600000000" Dst="0" />
<file name="atras3__o.png" server="web1420.ixwebhosting.com//imagenes360.net/tresdecito/" local="131353136486715038" remote="131353176600000000" Dst="0" />
<file name="atras3__o.svg" server="web1420.ixwebhosting.com//imagenes360.net/tresdecito/" local="131353136486725039" remote="131353176600000000" Dst="0" />
<file name="atras4.png" server="web1420.ixwebhosting.com//imagenes360.net/tresdecito/" local="131353136486735039" remote="131353176600000000" Dst="0" />
<file name="atras4.svg" server="web1420.ixwebhosting.com//imagenes360.net/tresdecito/" local="131353136486745040" remote="131353176600000000" Dst="0" />
<file name="atras4__o.png" server="web1420.ixwebhosting.com//imagenes360.net/tresdecito/" local="131353136486805043" remote="131353176600000000" Dst="0" />
<file name="atras4__o.svg" server="web1420.ixwebhosting.com//imagenes360.net/tresdecito/" local="131353136486815044" remote="131353176600000000" Dst="0" />
<file name="atras__o.png" server="web1420.ixwebhosting.com//imagenes360.net/tresdecito/" local="131353136486825044" remote="131353176600000000" Dst="0" />
<file name="atras__o.svg" server="web1420.ixwebhosting.com//imagenes360.net/tresdecito/" local="131353136486835045" remote="131353176600000000" Dst="0" />
<file name="comosehizo_06_o_0.jpg" server="web1420.ixwebhosting.com//imagenes360.net/tresdecito/" local="131353136663855170" remote="131353176600000000" Dst="0" />
<file name="comosehizo_06_o_1.jpg" server="web1420.ixwebhosting.com//imagenes360.net/tresdecito/" local="131353136664645215" remote="131353177200000000" Dst="0" />
<file name="comosehizo_06_o_2.jpg" server="web1420.ixwebhosting.com//imagenes360.net/tresdecito/" local="131353136665275251" remote="131353177200000000" Dst="0" />
<file name="comosehizo_06_o_4.jpg" server="web1420.ixwebhosting.com//imagenes360.net/tresdecito/" local="131353136666485320" remote="131353177200000000" Dst="0" />
<file name="comosehizo_06_o_3.jpg" server="web1420.ixwebhosting.com//imagenes360.net/tresdecito/" local="131353136665895287" remote="131353177200000000" Dst="0" />
<file name="hsimage.png" server="web1420.ixwebhosting.com//imagenes360.net/tresdecito/" local="131353136486845046" remote="131353177200000000" Dst="0" />
<file name="hsimage.svg" server="web1420.ixwebhosting.com//imagenes360.net/tresdecito/" local="131353136486855046" remote="131353177200000000" Dst="0" />
<file name="hsimage__o.png" server="web1420.ixwebhosting.com//imagenes360.net/tresdecito/" local="131353136486865047" remote="131353177200000000" Dst="0" />
<file name="hsimage__o.svg" server="web1420.ixwebhosting.com//imagenes360.net/tresdecito/" local="131353136486875047" remote="131353177200000000" Dst="0" />
<file name="comosehizo_06_o_5.jpg" server="web1420.ixwebhosting.com//imagenes360.net/tresdecito/" local="131353136667165359" remote="131353177200000000" Dst="0" />
<file name="kiosko_T_05_o_0.jpg" server="web1420.ixwebhosting.com//imagenes360.net/tresdecito/" local="131353136628043122" remote="131353177200000000" Dst="0" />
<file name="kiosko_T_05_o_1.jpg" server="web1420.ixwebhosting.com//imagenes360.net/tresdecito/" local="131353136628753162" remote="131353177200000000" Dst="0" />
<file name="kiosko_T_05_o_2.jpg" server="web1420.ixwebhosting.com//imagenes360.net/tresdecito/" local="131353136629423201" remote="131353177200000000" Dst="0" />
<file name="kiosko_T_05_o_3.jpg" server="web1420.ixwebhosting.com//imagenes360.net/tresdecito/" local="131353136630153242" remote="131353177200000000" Dst="0" />
<file name="kiosko_T_05_o_4.jpg" server="web1420.ixwebhosting.com//imagenes360.net/tresdecito/" local="131353136630773278" remote="131353177200000000" Dst="0" />
<file name="picture.png" server="web1420.ixwebhosting.com//imagenes360.net/tresdecito/" local="131353136486885048" remote="131353177200000000" Dst="0" />
<file name="picture.svg" server="web1420.ixwebhosting.com//imagenes360.net/tresdecito/" local="131353136486895048" remote="131353177200000000" Dst="0" />
<file name="kiosko_T_05_o_5.jpg" server="web1420.ixwebhosting.com//imagenes360.net/tresdecito/" local="131353136634733504" remote="131353177200000000" Dst="0" />
<file name="picture0.png" server="web1420.ixwebhosting.com//imagenes360.net/tresdecito/" local="131353136486895048" remote="131353177200000000" Dst="0" />
<file name="picture0.svg" server="web1420.ixwebhosting.com//imagenes360.net/tresdecito/" local="131353136486935051" remote="131353177200000000" Dst="0" />
<file name="picture0__o.svg" server="web1420.ixwebhosting.com//imagenes360.net/tresdecito/" local="131353136487155063" remote="131353177200000000" Dst="0" />
<file name="picture0__o.png" server="web1420.ixwebhosting.com//imagenes360.net/tresdecito/" local="131353136486965052" remote="131353177200000000" Dst="0" />
<file name="picture__o.png" server="web1420.ixwebhosting.com//imagenes360.net/tresdecito/" local="131353136487165064" remote="131353177200000000" Dst="0" />
<file name="picture__o.svg" server="web1420.ixwebhosting.com//imagenes360.net/tresdecito/" local="131353136487175064" remote="131353177200000000" Dst="0" />
<file name="skin_snd_camera.mp3" server="web1420.ixwebhosting.com//imagenes360.net/tresdecito/" local="131353136667175360" remote="131353177200000000" Dst="0" />
<file name="skin_snd_click_close.mp3" server="web1420.ixwebhosting.com//imagenes360.net/tresdecito/" local="131353136667225363" remote="131353177200000000" Dst="0" />
<file name="stage_total_03_o_0.jpg" server="web1420.ixwebhosting.com//imagenes360.net/tresdecito/" local="131353136612502233" remote="131353177200000000" Dst="0" />
<file name="stage_total_03_o_1.jpg" server="web1420.ixwebhosting.com//imagenes360.net/tresdecito/" local="131353136613132269" remote="131353177200000000" Dst="0" />
<file name="stage_total_03_o_2.jpg" server="web1420.ixwebhosting.com//imagenes360.net/tresdecito/" local="131353136613762305" remote="131353177200000000" Dst="0" />
<file name="stage_total_03_o_4.jpg" server="web1420.ixwebhosting.com//imagenes360.net/tresdecito/" local="131353136615572408" remote="131353177200000000" Dst="0" />
<file name="stage_total_03_o_3.jpg" server="web1420.ixwebhosting.com//imagenes360.net/tresdecito/" local="131353136614392341" remote="131353177200000000" Dst="0" />
<file name="stage_total_03_o_5.jpg" server="web1420.ixwebhosting.com//imagenes360.net/tresdecito/" local="131353136616262448" remote="131353177200000000" Dst="0" />
<file name="Terraza_baja_PH_o_1.jpg" server="web1420.ixwebhosting.com//imagenes360.net/tresdecito/" local="131353136548838591" remote="131353177200000000" Dst="0" />
<file name="Terraza_baja_PH_o_0.jpg" server="web1420.ixwebhosting.com//imagenes360.net/tresdecito/" local="131353136548218556" remote="131353177200000000" Dst="0" />
<file name="Terraza_baja_PH_o_3.jpg" server="web1420.ixwebhosting.com//imagenes360.net/tresdecito/" local="131353136550068662" remote="131353177800000000" Dst="0" />
<file name="Terraza_baja_PH_o_2.jpg" server="web1420.ixwebhosting.com//imagenes360.net/tresdecito/" local="131353136549458627" remote="131353177800000000" Dst="0" />
<file name="Terraza_baja_PH_o_4.jpg" server="web1420.ixwebhosting.com//imagenes360.net/tresdecito/" local="131353136550908710" remote="131353177800000000" Dst="0" />
<file name="Terraza_baja_PH_o_5.jpg" server="web1420.ixwebhosting.com//imagenes360.net/tresdecito/" local="131353136551528745" remote="131353178400000000" Dst="0" />
</dwsync>